pgpipeline/__init__.py
pgpipeline/core.py
pgpipeline/helpers.py
pgpipeline-0.4.0.dist-info/DESCRIPTION.rst
pgpipeline-0.4.0.dist-info/METADATA
pgpipeline-0.4.0.dist-info/RECORD
pgpipeline-0.4.0.dist-info/WHEEL
pgpipeline-0.4.0.dist-info/metadata.json
pgpipeline-0.4.0.dist-info/top_level.txt
