Metadata-Version: 2.0
Name: pgpipeline
Version: 0.4.0
Summary: Pgpipeline: An automatic postgres item pipeline for Scrapy
Home-page: https://github.com/jondot/pgpipeline
Author: Dotan Nahum
Author-email: jondotan@gmail.com
License: Copyright (c) 2012, Dotan Nahum
Requires-Dist: dataset
